LICENSE
README.md
lyynew.py
setup.py
lyynew.egg-info/PKG-INFO
lyynew.egg-info/SOURCES.txt
lyynew.egg-info/dependency_links.txt
lyynew.egg-info/top_level.txt