Metadata-Version: 2.1
Name: lyynew
Version: 1.2
Summary: lyy new data for lyy
Author: yy
Author-email: 
License: MIT
License-File: LICENSE
